rcsb/__init__.py
rcsb/utils/__init__.py
rcsb/utils/config/ConfigUtil.py
rcsb/utils/config/ExampleHelper.py
rcsb/utils/config/__init__.py
rcsb.utils.config-0.41.dist-info/LICENSE
rcsb.utils.config-0.41.dist-info/METADATA
rcsb.utils.config-0.41.dist-info/WHEEL
rcsb.utils.config-0.41.dist-info/top_level.txt
rcsb.utils.config-0.41.dist-info/RECORD
