Metadata-Version: 2.1
Name: rcsb.utils.config
Version: 0.41
Summary: RCSB Python Configuration Utilities
Home-page: https://github.com/rcsb/py-rcsb_utils_config
Author: John Westbrook
Author-email: john.westbrook@rcsb.org
License: Apache 2.0
Classifier: Development Status :: 3 - Alpha
Classifier: Intended Audience :: Developers
Classifier: Natural Language :: English
Classifier: License :: OSI Approved :: Apache Software License
Classifier: Programming Language :: Python
Classifier: Programming Language :: Python :: 3
Classifier: Programming Language :: Python :: 3.10
License-File: LICENSE
Requires-Dist: future
Requires-Dist: configparser; python_version < "3.0"
Requires-Dist: ruamel.yaml
Requires-Dist: PyNaCl>=1.3.0
Requires-Dist: rcsb.utils.io>=0.63
Provides-Extra: dev
Requires-Dist: check-manifest; extra == "dev"
Provides-Extra: test
Requires-Dist: coverage; extra == "test"
